cogstack_model_gateway_client/__init__.py
cogstack_model_gateway_client/client.py
cogstack_model_gateway/common/__init__.py
cogstack_model_gateway/common/config.py
cogstack_model_gateway/common/containers.py
cogstack_model_gateway/common/db.py
cogstack_model_gateway/common/exceptions.py
cogstack_model_gateway/common/logging.py
cogstack_model_gateway/common/object_store.py
cogstack_model_gateway/common/queue.py
cogstack_model_gateway/common/tasks.py
cogstack_model_gateway/common/tracking.py
cogstack_model_gateway/common/utils.py
cogstack_model_gateway/gateway/Dockerfile
cogstack_model_gateway/gateway/__init__.py
cogstack_model_gateway/gateway/core/models.py
cogstack_model_gateway/gateway/core/priority.py
cogstack_model_gateway/gateway/main.py
cogstack_model_gateway/gateway/routers/models.py
cogstack_model_gateway/gateway/routers/tasks.py
cogstack_model_gateway/gateway/routers/utils.py
cogstack_model_gateway/ripper/Dockerfile
cogstack_model_gateway/ripper/__init__.py
cogstack_model_gateway/ripper/main.py
cogstack_model_gateway/scheduler/Dockerfile
cogstack_model_gateway/scheduler/__init__.py
cogstack_model_gateway/scheduler/main.py
cogstack_model_gateway/scheduler/scheduler.py
cogstack_model_gateway-0.1.0.dist-info/LICENSE
cogstack_model_gateway-0.1.0.dist-info/METADATA
cogstack_model_gateway-0.1.0.dist-info/WHEEL
cogstack_model_gateway-0.1.0.dist-info/RECORD
