Metadata-Version: 2.3
Name: cogstack-model-gateway
Version: 0.1.0
Summary: A Gateway for accessing Cogstack ModelServe instances
License: Apache-2.0
Author: Phoevos Kalemkeris
Author-email: phoevos.kalemkeris@ucl.ac.uk
Requires-Python: >=3.12,<4.0
Classifier: License :: OSI Approved :: Apache Software License
Classifier: Programming Language :: Python :: 3
Classifier: Programming Language :: Python :: 3.12
Classifier: Programming Language :: Python :: 3.13
Requires-Dist: docker (>=7.1.0,<8.0.0)
Requires-Dist: fastapi[standard] (>=0.115.5,<0.116.0)
Requires-Dist: minio (>=7.2.12,<8.0.0)
Requires-Dist: mlflow (>=2.18.0,<3.0.0)
Requires-Dist: pika (>=1.3.2,<2.0.0)
Requires-Dist: psycopg2-binary (>=2.9.10,<3.0.0)
Requires-Dist: pydantic-settings (>=2.6.1,<3.0.0)
Requires-Dist: python-dotenv (>=1.0.1,<2.0.0)
Requires-Dist: python-multipart (>=0.0.19,<0.0.20)
Requires-Dist: requests (>=2.32.3,<3.0.0)
Requires-Dist: sqlmodel (>=0.0.22,<0.0.23)
Requires-Dist: tenacity (>=9.0.0,<10.0.0)
